click_web/__init__.py
click_web/exceptions.py
click_web/web_click_types.py
click_web/resources/__init__.py
click_web/resources/cmd_exec.py
click_web/resources/cmd_form.py
click_web/resources/index.py
click_web/resources/input_fields.py
click_web/static/click_web.css
click_web/static/copy_to_clipboard.js
click_web/static/open_form.js
click_web/static/panes.css
click_web/static/panes.js
click_web/static/post_and_read.js
click_web/static/pure.css
click_web/static/split.js
click_web/templates/command_form.html.j2
click_web/templates/form_macros.html.j2
click_web/templates/show_tree.html.j2
tests/__init__.py
tests/conftest.py
tests/test_click_web.py
tests/test_flask_get.py
tests/test_flask_post.py
tests/test_request_parsing.py
tests/fixtures/__init__.py
tests/fixtures/click_fixtures.py
tests/fixtures/flask_fixtures.py
tests/fixtures/script/__init__.py
tests/fixtures/script/a_script.py
tests/fixtures/script/app.py
click_web-0.8.6.dist-info/AUTHORS.rst
click_web-0.8.6.dist-info/LICENSE
click_web-0.8.6.dist-info/METADATA
click_web-0.8.6.dist-info/WHEEL
click_web-0.8.6.dist-info/top_level.txt
click_web-0.8.6.dist-info/RECORD
