Metadata-Version: 2.1
Name: click-web
Version: 0.8.6
Summary: Serve click scripts over the web with minimal effort.
Home-page: https://github.com/fredrik-corneliusson/click-web
Author: Fredrik Corneliusson
Author-email: fredrik.corneliusson@gmail.com
License: MIT
Classifier: Development Status :: 3 - Alpha
Classifier: Intended Audience :: Developers
Classifier: License :: OSI Approved :: MIT License
Classifier: Operating System :: OS Independent
Classifier: Topic :: Software Development :: User Interfaces
Classifier: Topic :: Internet :: WWW/HTTP :: Dynamic Content
Classifier: Topic :: System :: Shells
Classifier: Topic :: Utilities
Classifier: Programming Language :: Python
Classifier: Programming Language :: Python :: 3
Classifier: Programming Language :: Python :: 3.8
Classifier: Programming Language :: Python :: 3.9
Classifier: Programming Language :: Python :: 3.10
Classifier: Programming Language :: Python :: 3.11
Requires-Python: >=3.8
License-File: LICENSE
License-File: AUTHORS.rst
Requires-Dist: click >=8.0
Requires-Dist: Flask >=2.3.2
Requires-Dist: Jinja2 >=3.1.3
Requires-Dist: flask-httpauth >=3.2.4
Provides-Extra: dev
Requires-Dist: pytest >=6.2 ; extra == 'dev'
Requires-Dist: flake8 >=3.9 ; extra == 'dev'
Requires-Dist: beautifulsoup4 >=4.9 ; extra == 'dev'
Requires-Dist: isort >=5.8 ; extra == 'dev'
Requires-Dist: twine >=3.4 ; extra == 'dev'
Requires-Dist: wheel ; extra == 'dev'
